cartpolev0dqn
