Metadata-Version: 2.1
Name: cartpolev0dqn
Version: 0.1.2
Summary: A package for CartPole V0 problem using dqn
Home-page: https://github.com/AimAlex/CartPoleV0DQN
Author: Jiangbei Li
Author-email: lijiangbei@4paradigm.com
License: UNKNOWN
Platform: UNKNOWN
Classifier: Programming Language :: Python :: 2.7
Classifier: License :: OSI Approved :: MIT License
Classifier: Operating System :: POSIX :: Linux
